[
  {
    "id": 1,
    "name": "Enterprise Fortress Gateway",
    "price": "1.889,00 €",
    "imageLink": "https://raw.githubusercontent.com/rysfa/JSONDataExample/main/Product_1.png",
    "productLink": "https://raw.githubusercontent.com/rysfa/JSONDataExample/main/Product_1.json"
  },
  {
    "id": 2,
    "name": "Dream Machine Pro Max",
    "price": "553,00 €",
    "imageLink": "https://raw.githubusercontent.com/rysfa/JSONDataExample/main/Product_2.png",
    "productLink": "https://raw.githubusercontent.com/rysfa/JSONDataExample/main/Product_2.json"
  },
  {
    "id": 3,
    "name": "Cloud Gateway Max",
    "price": "322,00 €",
    "imageLink": "https://raw.githubusercontent.com/rysfa/JSONDataExample/main/Product_3.png",
    "productLink": "https://raw.githubusercontent.com/rysfa/JSONDataExample/main/Product_3.json"
  }
]
